comb ckt/muxes/mux8x1/mux8x1.v
module mux8x1 (
    input  [7:0] I0,
    input  [7:0] I1,
    input  [7:0] I2,
    input  [7:0] I3,
    input  [7:0] I4,
    input  [7:0] I5,
    input  [7:0] I6,
    input  [7:0] I7,
    input [2:0] sel,
    output [7:0] Y

);

assign Y = (sel == 3'b000) ? I0 : 
(sel == 3'b001) ? I1 : 
(sel == 3'b010) ? I2 : 
(sel == 3'b011) ? I3 : 
(sel == 3'b100) ? I4 : 
(sel == 3'b101) ? I5 : 
(sel == 3'b110) ? I6 : 
I7;
    
endmodule

comb ckt/muxes/mux8x1/mux8x1_tb.v

module mux8x1_tb ();

reg [7:0] I[7:0];
reg [2:0] sel;
wire [7:0] Y;

mux8x1 m8 (I[0], I[1], I[2], I[3], I[4], I[5], I[6], I[7], sel, Y);

initial begin
    $dumpfile ("mux8x1.vcd");
    $dumpvars (0, mux8x1_tb);
    
    I[0] = 8'h12;
    I[1] = 8'h13;
    I[2] = 8'h14;
    I[3] = 8'h15;
    I[4] = 8'h16;
    I[5] = 8'h17;
    I[6] = 8'h18;
    I[7] = 8'h19;

    sel = 3'b000;
    #10 sel = 3'b001;
    #10 sel = 3'b010;
    #10 sel = 3'b011;
    #10 sel = 3'b100;
    #10 sel = 3'b101;
    #10 sel = 3'b110;
    #10 sel = 3'b111;
    #10;
    $finish ;
end
endmodule

comb ckt/muxes/mux8x1/mux8x1.vcd
$date
	Mon May 25 10:32:12 2026
$end
$version
	Icarus Verilog
$end
$timescale
	1s
$end
$scope module mux8x1_tb $end
$var wire 8 ! Y [7:0] $end
$var reg 3 " sel [2:0] $end
$scope module m8 $end
$var wire 8 # I0 [7:0] $end
$var wire 8 $ I1 [7:0] $end
$var wire 8 % I2 [7:0] $end
$var wire 8 & I3 [7:0] $end
$var wire 8 ' I4 [7:0] $end
$var wire 8 ( I5 [7:0] $end
$var wire 8 ) I6 [7:0] $end
$var wire 8 * I7 [7:0] $end
$var wire 3 + sel [2:0] $end
$var wire 8 , Y [7:0] $end
$upscope $end
$upscope $end
$enddefinitions $end
$comment Show the parameter values. $end
$dumpall
$end
#0
$dumpvars
b10010 ,
b0 +
b11001 *
b11000 )
b10111 (
b10110 '
b10101 &
b10100 %
b10011 $
b10010 #
b0 "
b10010 !
$end
#10
b10011 !
b10011 ,
b1 "
b1 +
#20
b10100 !
b10100 ,
b10 "
b10 +
#30
b10101 !
b10101 ,
b11 "
b11 +
#40
b10110 !
b10110 ,
b100 "
b100 +
#50
b10111 !
b10111 ,
b101 "
b101 +
#60
b11000 !
b11000 ,
b110 "
b110 +
#70
b11001 !
b11001 ,
b111 "
b111 +
